xsd2doc/__init__.py
xsd2doc/log.py
xsd2doc/main.py
xsd2doc/markdown.py
xsd2doc/parse.py
xsd2doc/templates/template-dynamic.md.j2
xsd2doc-0.1.3.dist-info/licenses/LICENSE
xsd2doc-0.1.3.dist-info/METADATA
xsd2doc-0.1.3.dist-info/WHEEL
xsd2doc-0.1.3.dist-info/entry_points.txt
xsd2doc-0.1.3.dist-info/top_level.txt
xsd2doc-0.1.3.dist-info/RECORD
