Metadata-Version: 2.4
Name: xsd2doc
Version: 0.1.3
Summary: xsd2doc: A tool to generate markdown documentation from XSD files.
Author: YammyToast
License: MIT License
Requires-Python: >=3.9
License-File: LICENSE
Requires-Dist: jinja2
Requires-Dist: pyyaml
Dynamic: license-file
Dynamic: requires-python
